[
    {
        "name": "ability",
        "data": {
            "highres": "./images/ability.png",
            "thumb": "./thumb/ability.png"
        }
    },
    {
        "name": "able",
        "data": {
            "highres": "./images/able.png",
            "thumb": "./thumb/able.png"
        }
    },
    {
        "name": "aboard",
        "data": {
            "highres": "./images/aboard.png",
            "thumb": "./thumb/aboard.png"
        }
    },
    {
        "name": "about",
        "data": {
            "highres": "./images/about.png",
            "thumb": "./thumb/about.png"
        }
    },
    {
        "name": "above",
        "data": {
            "highres": "./images/above.png",
            "thumb": "./thumb/above.png"
        }
    },
    {
        "name": "accept",
        "data": {
            "highres": "./images/accept.png",
            "thumb": "./thumb/accept.png"
        }
    },
    {
        "name": "accident",
        "data": {
            "highres": "./images/accident.png",
            "thumb": "./thumb/accident.png"
        }
    },
    {
        "name": "according",
        "data": {
            "highres": "./images/according.png",
            "thumb": "./thumb/according.png"
        }
    },
    {
        "name": "account",
        "data": {
            "highres": "./images/account.png",
            "thumb": "./thumb/account.png"
        }
    },
    {
        "name": "accurate",
        "data": {
            "highres": "./images/accurate.png",
            "thumb": "./thumb/accurate.png"
        }
    },
    {
        "name": "acres",
        "data": {
            "highres": "./images/acres.png",
            "thumb": "./thumb/acres.png"
        }
    },
    {
        "name": "across",
        "data": {
            "highres": "./images/across.png",
            "thumb": "./thumb/across.png"
        }
    },
    {
        "name": "act",
        "data": {
            "highres": "./images/act.png",
            "thumb": "./thumb/act.png"
        }
    },
    {
        "name": "action",
        "data": {
            "highres": "./images/action.png",
            "thumb": "./thumb/action.png"
        }
    },
    {
        "name": "active",
        "data": {
            "highres": "./images/active.png",
            "thumb": "./thumb/active.png"
        }
    },
    {
        "name": "activity",
        "data": {
            "highres": "./images/activity.png",
            "thumb": "./thumb/activity.png"
        }
    },
    {
        "name": "actual",
        "data": {
            "highres": "./images/actual.png",
            "thumb": "./thumb/actual.png"
        }
    },
    {
        "name": "actually",
        "data": {
            "highres": "./images/actually.png",
            "thumb": "./thumb/actually.png"
        }
    },
    {
        "name": "add",
        "data": {
            "highres": "./images/add.png",
            "thumb": "./thumb/add.png"
        }
    },
    {
        "name": "addition",
        "data": {
            "highres": "./images/addition.png",
            "thumb": "./thumb/addition.png"
        }
    },
    {
        "name": "additional",
        "data": {
            "highres": "./images/additional.png",
            "thumb": "./thumb/additional.png"
        }
    },
    {
        "name": "adjective",
        "data": {
            "highres": "./images/adjective.png",
            "thumb": "./thumb/adjective.png"
        }
    },
    {
        "name": "adult",
        "data": {
            "highres": "./images/adult.png",
            "thumb": "./thumb/adult.png"
        }
    },
    {
        "name": "adventure",
        "data": {
            "highres": "./images/adventure.png",
            "thumb": "./thumb/adventure.png"
        }
    },
    {
        "name": "advice",
        "data": {
            "highres": "./images/advice.png",
            "thumb": "./thumb/advice.png"
        }
    },
    {
        "name": "affect",
        "data": {
            "highres": "./images/affect.png",
            "thumb": "./thumb/affect.png"
        }
    },
    {
        "name": "afraid",
        "data": {
            "highres": "./images/afraid.png",
            "thumb": "./thumb/afraid.png"
        }
    },
    {
        "name": "after",
        "data": {
            "highres": "./images/after.png",
            "thumb": "./thumb/after.png"
        }
    },
    {
        "name": "afternoon",
        "data": {
            "highres": "./images/afternoon.png",
            "thumb": "./thumb/afternoon.png"
        }
    },
    {
        "name": "again",
        "data": {
            "highres": "./images/again.png",
            "thumb": "./thumb/again.png"
        }
    },
    {
        "name": "against",
        "data": {
            "highres": "./images/against.png",
            "thumb": "./thumb/against.png"
        }
    },
    {
        "name": "age",
        "data": {
            "highres": "./images/age.png",
            "thumb": "./thumb/age.png"
        }
    },
    {
        "name": "ago",
        "data": {
            "highres": "./images/ago.png",
            "thumb": "./thumb/ago.png"
        }
    },
    {
        "name": "agree",
        "data": {
            "highres": "./images/agree.png",
            "thumb": "./thumb/agree.png"
        }
    },
    {
        "name": "ahead",
        "data": {
            "highres": "./images/ahead.png",
            "thumb": "./thumb/ahead.png"
        }
    },
    {
        "name": "aid",
        "data": {
            "highres": "./images/aid.png",
            "thumb": "./thumb/aid.png"
        }
    },
    {
        "name": "air",
        "data": {
            "highres": "./images/air.png",
            "thumb": "./thumb/air.png"
        }
    },
    {
        "name": "airplane",
        "data": {
            "highres": "./images/airplane.png",
            "thumb": "./thumb/airplane.png"
        }
    },
    {
        "name": "alike",
        "data": {
            "highres": "./images/alike.png",
            "thumb": "./thumb/alike.png"
        }
    },
    {
        "name": "alive",
        "data": {
            "highres": "./images/alive.png",
            "thumb": "./thumb/alive.png"
        }
    },
    {
        "name": "all",
        "data": {
            "highres": "./images/all.png",
            "thumb": "./thumb/all.png"
        }
    },
    {
        "name": "allow",
        "data": {
            "highres": "./images/allow.png",
            "thumb": "./thumb/allow.png"
        }
    },
    {
        "name": "almost",
        "data": {
            "highres": "./images/almost.png",
            "thumb": "./thumb/almost.png"
        }
    },
    {
        "name": "alone",
        "data": {
            "highres": "./images/alone.png",
            "thumb": "./thumb/alone.png"
        }
    },
    {
        "name": "along",
        "data": {
            "highres": "./images/along.png",
            "thumb": "./thumb/along.png"
        }
    },
    {
        "name": "aloud",
        "data": {
            "highres": "./images/aloud.png",
            "thumb": "./thumb/aloud.png"
        }
    },
    {
        "name": "alphabet",
        "data": {
            "highres": "./images/alphabet.png",
            "thumb": "./thumb/alphabet.png"
        }
    },
    {
        "name": "already",
        "data": {
            "highres": "./images/already.png",
            "thumb": "./thumb/already.png"
        }
    },
    {
        "name": "also",
        "data": {
            "highres": "./images/also.png",
            "thumb": "./thumb/also.png"
        }
    },
    {
        "name": "although",
        "data": {
            "highres": "./images/although.png",
            "thumb": "./thumb/although.png"
        }
    },
    {
        "name": "am",
        "data": {
            "highres": "./images/am.png",
            "thumb": "./thumb/am.png"
        }
    },
    {
        "name": "among",
        "data": {
            "highres": "./images/among.png",
            "thumb": "./thumb/among.png"
        }
    },
    {
        "name": "amount",
        "data": {
            "highres": "./images/amount.png",
            "thumb": "./thumb/amount.png"
        }
    },
    {
        "name": "ancient",
        "data": {
            "highres": "./images/ancient.png",
            "thumb": "./thumb/ancient.png"
        }
    },
    {
        "name": "angle",
        "data": {
            "highres": "./images/angle.png",
            "thumb": "./thumb/angle.png"
        }
    },
    {
        "name": "angry",
        "data": {
            "highres": "./images/angry.png",
            "thumb": "./thumb/angry.png"
        }
    },
    {
        "name": "animal",
        "data": {
            "highres": "./images/animal.png",
            "thumb": "./thumb/animal.png"
        }
    },
    {
        "name": "announced",
        "data": {
            "highres": "./images/announced.png",
            "thumb": "./thumb/announced.png"
        }
    },
    {
        "name": "another",
        "data": {
            "highres": "./images/another.png",
            "thumb": "./thumb/another.png"
        }
    },
    {
        "name": "answer",
        "data": {
            "highres": "./images/answer.png",
            "thumb": "./thumb/answer.png"
        }
    },
    {
        "name": "ants",
        "data": {
            "highres": "./images/ants.png",
            "thumb": "./thumb/ants.png"
        }
    },
    {
        "name": "any",
        "data": {
            "highres": "./images/any.png",
            "thumb": "./thumb/any.png"
        }
    },
    {
        "name": "anybody",
        "data": {
            "highres": "./images/anybody.png",
            "thumb": "./thumb/anybody.png"
        }
    },
    {
        "name": "anyone",
        "data": {
            "highres": "./images/anyone.png",
            "thumb": "./thumb/anyone.png"
        }
    },
    {
        "name": "anything",
        "data": {
            "highres": "./images/anything.png",
            "thumb": "./thumb/anything.png"
        }
    },
    {
        "name": "anyway",
        "data": {
            "highres": "./images/anyway.png",
            "thumb": "./thumb/anyway.png"
        }
    },
    {
        "name": "anywhere",
        "data": {
            "highres": "./images/anywhere.png",
            "thumb": "./thumb/anywhere.png"
        }
    },
    {
        "name": "apart",
        "data": {
            "highres": "./images/apart.png",
            "thumb": "./thumb/apart.png"
        }
    },
    {
        "name": "apartment",
        "data": {
            "highres": "./images/apartment.png",
            "thumb": "./thumb/apartment.png"
        }
    },
    {
        "name": "appearance",
        "data": {
            "highres": "./images/appearance.png",
            "thumb": "./thumb/appearance.png"
        }
    },
    {
        "name": "apple",
        "data": {
            "highres": "./images/apple.png",
            "thumb": "./thumb/apple.png"
        }
    },
    {
        "name": "applied",
        "data": {
            "highres": "./images/applied.png",
            "thumb": "./thumb/applied.png"
        }
    },
    {
        "name": "appropriate",
        "data": {
            "highres": "./images/appropriate.png",
            "thumb": "./thumb/appropriate.png"
        }
    },
    {
        "name": "are",
        "data": {
            "highres": "./images/are.png",
            "thumb": "./thumb/are.png"
        }
    },
    {
        "name": "area",
        "data": {
            "highres": "./images/area.png",
            "thumb": "./thumb/area.png"
        }
    },
    {
        "name": "arm",
        "data": {
            "highres": "./images/arm.png",
            "thumb": "./thumb/arm.png"
        }
    },
    {
        "name": "army",
        "data": {
            "highres": "./images/army.png",
            "thumb": "./thumb/army.png"
        }
    },
    {
        "name": "around",
        "data": {
            "highres": "./images/around.png",
            "thumb": "./thumb/around.png"
        }
    },
    {
        "name": "arrange",
        "data": {
            "highres": "./images/arrange.png",
            "thumb": "./thumb/arrange.png"
        }
    },
    {
        "name": "arrangement",
        "data": {
            "highres": "./images/arrangement.png",
            "thumb": "./thumb/arrangement.png"
        }
    },
    {
        "name": "arrive",
        "data": {
            "highres": "./images/arrive.png",
            "thumb": "./thumb/arrive.png"
        }
    },
    {
        "name": "arrow",
        "data": {
            "highres": "./images/arrow.png",
            "thumb": "./thumb/arrow.png"
        }
    },
    {
        "name": "art",
        "data": {
            "highres": "./images/art.png",
            "thumb": "./thumb/art.png"
        }
    },
    {
        "name": "article",
        "data": {
            "highres": "./images/article.png",
            "thumb": "./thumb/article.png"
        }
    },
    {
        "name": "as",
        "data": {
            "highres": "./images/as.png",
            "thumb": "./thumb/as.png"
        }
    },
    {
        "name": "aside",
        "data": {
            "highres": "./images/aside.png",
            "thumb": "./thumb/aside.png"
        }
    },
    {
        "name": "ask",
        "data": {
            "highres": "./images/ask.png",
            "thumb": "./thumb/ask.png"
        }
    },
    {
        "name": "asleep",
        "data": {
            "highres": "./images/asleep.png",
            "thumb": "./thumb/asleep.png"
        }
    },
    {
        "name": "at",
        "data": {
            "highres": "./images/at.png",
            "thumb": "./thumb/at.png"
        }
    },
    {
        "name": "ate",
        "data": {
            "highres": "./images/ate.png",
            "thumb": "./thumb/ate.png"
        }
    },
    {
        "name": "atmosphere",
        "data": {
            "highres": "./images/atmosphere.png",
            "thumb": "./thumb/atmosphere.png"
        }
    },
    {
        "name": "atom",
        "data": {
            "highres": "./images/atom.png",
            "thumb": "./thumb/atom.png"
        }
    },
    {
        "name": "atomic",
        "data": {
            "highres": "./images/atomic.png",
            "thumb": "./thumb/atomic.png"
        }
    },
    {
        "name": "attached",
        "data": {
            "highres": "./images/attached.png",
            "thumb": "./thumb/attached.png"
        }
    },
    {
        "name": "attack",
        "data": {
            "highres": "./images/attack.png",
            "thumb": "./thumb/attack.png"
        }
    },
    {
        "name": "attempt",
        "data": {
            "highres": "./images/attempt.png",
            "thumb": "./thumb/attempt.png"
        }
    },
    {
        "name": "attention",
        "data": {
            "highres": "./images/attention.png",
            "thumb": "./thumb/attention.png"
        }
    },
    {
        "name": "audience",
        "data": {
            "highres": "./images/audience.png",
            "thumb": "./thumb/audience.png"
        }
    },
    {
        "name": "author",
        "data": {
            "highres": "./images/author.png",
            "thumb": "./thumb/author.png"
        }
    },
    {
        "name": "automobile",
        "data": {
            "highres": "./images/automobile.png",
            "thumb": "./thumb/automobile.png"
        }
    },
    {
        "name": "available",
        "data": {
            "highres": "./images/available.png",
            "thumb": "./thumb/available.png"
        }
    },
    {
        "name": "average",
        "data": {
            "highres": "./images/average.png",
            "thumb": "./thumb/average.png"
        }
    },
    {
        "name": "avoid",
        "data": {
            "highres": "./images/avoid.png",
            "thumb": "./thumb/avoid.png"
        }
    },
    {
        "name": "aware",
        "data": {
            "highres": "./images/aware.png",
            "thumb": "./thumb/aware.png"
        }
    },
    {
        "name": "away",
        "data": {
            "highres": "./images/away.png",
            "thumb": "./thumb/away.png"
        }
    },
    {
        "name": "baby",
        "data": {
            "highres": "./images/baby.png",
            "thumb": "./thumb/baby.png"
        }
    },
    {
        "name": "back",
        "data": {
            "highres": "./images/back.png",
            "thumb": "./thumb/back.png"
        }
    },
    {
        "name": "bad",
        "data": {
            "highres": "./images/bad.png",
            "thumb": "./thumb/bad.png"
        }
    },
    {
        "name": "badly",
        "data": {
            "highres": "./images/badly.png",
            "thumb": "./thumb/badly.png"
        }
    },
    {
        "name": "bag",
        "data": {
            "highres": "./images/bag.png",
            "thumb": "./thumb/bag.png"
        }
    },
    {
        "name": "balance",
        "data": {
            "highres": "./images/balance.png",
            "thumb": "./thumb/balance.png"
        }
    },
    {
        "name": "ball",
        "data": {
            "highres": "./images/ball.png",
            "thumb": "./thumb/ball.png"
        }
    },
    {
        "name": "balloon",
        "data": {
            "highres": "./images/balloon.png",
            "thumb": "./thumb/balloon.png"
        }
    },
    {
        "name": "band",
        "data": {
            "highres": "./images/band.png",
            "thumb": "./thumb/band.png"
        }
    },
    {
        "name": "bank",
        "data": {
            "highres": "./images/bank.png",
            "thumb": "./thumb/bank.png"
        }
    },
    {
        "name": "bar",
        "data": {
            "highres": "./images/bar.png",
            "thumb": "./thumb/bar.png"
        }
    },
    {
        "name": "bare",
        "data": {
            "highres": "./images/bare.png",
            "thumb": "./thumb/bare.png"
        }
    },
    {
        "name": "bark",
        "data": {
            "highres": "./images/bark.png",
            "thumb": "./thumb/bark.png"
        }
    },
    {
        "name": "barn",
        "data": {
            "highres": "./images/barn.png",
            "thumb": "./thumb/barn.png"
        }
    },
    {
        "name": "base",
        "data": {
            "highres": "./images/base.png",
            "thumb": "./thumb/base.png"
        }
    },
    {
        "name": "baseball",
        "data": {
            "highres": "./images/baseball.png",
            "thumb": "./thumb/baseball.png"
        }
    },
    {
        "name": "basic",
        "data": {
            "highres": "./images/basic.png",
            "thumb": "./thumb/basic.png"
        }
    },
    {
        "name": "basis",
        "data": {
            "highres": "./images/basis.png",
            "thumb": "./thumb/basis.png"
        }
    },
    {
        "name": "basket",
        "data": {
            "highres": "./images/basket.png",
            "thumb": "./thumb/basket.png"
        }
    },
    {
        "name": "bat",
        "data": {
            "highres": "./images/bat.png",
            "thumb": "./thumb/bat.png"
        }
    },
    {
        "name": "battle",
        "data": {
            "highres": "./images/battle.png",
            "thumb": "./thumb/battle.png"
        }
    },
    {
        "name": "be",
        "data": {
            "highres": "./images/be.png",
            "thumb": "./thumb/be.png"
        }
    },
    {
        "name": "bean",
        "data": {
            "highres": "./images/bean.png",
            "thumb": "./thumb/bean.png"
        }
    },
    {
        "name": "bear",
        "data": {
            "highres": "./images/bear.png",
            "thumb": "./thumb/bear.png"
        }
    },
    {
        "name": "beat",
        "data": {
            "highres": "./images/beat.png",
            "thumb": "./thumb/beat.png"
        }
    },
    {
        "name": "beautiful",
        "data": {
            "highres": "./images/beautiful.png",
            "thumb": "./thumb/beautiful.png"
        }
    },
    {
        "name": "beauty",
        "data": {
            "highres": "./images/beauty.png",
            "thumb": "./thumb/beauty.png"
        }
    },
    {
        "name": "became",
        "data": {
            "highres": "./images/became.png",
            "thumb": "./thumb/became.png"
        }
    },
    {
        "name": "because",
        "data": {
            "highres": "./images/because.png",
            "thumb": "./thumb/because.png"
        }
    },
    {
        "name": "become",
        "data": {
            "highres": "./images/become.png",
            "thumb": "./thumb/become.png"
        }
    },
    {
        "name": "becoming",
        "data": {
            "highres": "./images/becoming.png",
            "thumb": "./thumb/becoming.png"
        }
    },
    {
        "name": "bee",
        "data": {
            "highres": "./images/bee.png",
            "thumb": "./thumb/bee.png"
        }
    },
    {
        "name": "been",
        "data": {
            "highres": "./images/been.png",
            "thumb": "./thumb/been.png"
        }
    },
    {
        "name": "before",
        "data": {
            "highres": "./images/before.png",
            "thumb": "./thumb/before.png"
        }
    },
    {
        "name": "began",
        "data": {
            "highres": "./images/began.png",
            "thumb": "./thumb/began.png"
        }
    },
    {
        "name": "beginning",
        "data": {
            "highres": "./images/beginning.png",
            "thumb": "./thumb/beginning.png"
        }
    },
    {
        "name": "begun",
        "data": {
            "highres": "./images/begun.png",
            "thumb": "./thumb/begun.png"
        }
    },
    {
        "name": "behavior",
        "data": {
            "highres": "./images/behavior.png",
            "thumb": "./thumb/behavior.png"
        }
    },
    {
        "name": "behind",
        "data": {
            "highres": "./images/behind.png",
            "thumb": "./thumb/behind.png"
        }
    },
    {
        "name": "being",
        "data": {
            "highres": "./images/being.png",
            "thumb": "./thumb/being.png"
        }
    },
    {
        "name": "believed",
        "data": {
            "highres": "./images/believed.png",
            "thumb": "./thumb/believed.png"
        }
    },
    {
        "name": "bell",
        "data": {
            "highres": "./images/bell.png",
            "thumb": "./thumb/bell.png"
        }
    },
    {
        "name": "belong",
        "data": {
            "highres": "./images/belong.png",
            "thumb": "./thumb/belong.png"
        }
    },
    {
        "name": "below",
        "data": {
            "highres": "./images/below.png",
            "thumb": "./thumb/below.png"
        }
    },
    {
        "name": "belt",
        "data": {
            "highres": "./images/belt.png",
            "thumb": "./thumb/belt.png"
        }
    },
    {
        "name": "bend",
        "data": {
            "highres": "./images/bend.png",
            "thumb": "./thumb/bend.png"
        }
    },
    {
        "name": "beneath",
        "data": {
            "highres": "./images/beneath.png",
            "thumb": "./thumb/beneath.png"
        }
    },
    {
        "name": "bent",
        "data": {
            "highres": "./images/bent.png",
            "thumb": "./thumb/bent.png"
        }
    },
    {
        "name": "beside",
        "data": {
            "highres": "./images/beside.png",
            "thumb": "./thumb/beside.png"
        }
    },
    {
        "name": "best",
        "data": {
            "highres": "./images/best.png",
            "thumb": "./thumb/best.png"
        }
    },
    {
        "name": "bet",
        "data": {
            "highres": "./images/bet.png",
            "thumb": "./thumb/bet.png"
        }
    },
    {
        "name": "better",
        "data": {
            "highres": "./images/better.png",
            "thumb": "./thumb/better.png"
        }
    },
    {
        "name": "between",
        "data": {
            "highres": "./images/between.png",
            "thumb": "./thumb/between.png"
        }
    },
    {
        "name": "beyond",
        "data": {
            "highres": "./images/beyond.png",
            "thumb": "./thumb/beyond.png"
        }
    },
    {
        "name": "bicycle",
        "data": {
            "highres": "./images/bicycle.png",
            "thumb": "./thumb/bicycle.png"
        }
    },
    {
        "name": "bigger",
        "data": {
            "highres": "./images/bigger.png",
            "thumb": "./thumb/bigger.png"
        }
    },
    {
        "name": "biggest",
        "data": {
            "highres": "./images/biggest.png",
            "thumb": "./thumb/biggest.png"
        }
    },
    {
        "name": "bill",
        "data": {
            "highres": "./images/bill.png",
            "thumb": "./thumb/bill.png"
        }
    },
    {
        "name": "birds",
        "data": {
            "highres": "./images/birds.png",
            "thumb": "./thumb/birds.png"
        }
    },
    {
        "name": "birth",
        "data": {
            "highres": "./images/birth.png",
            "thumb": "./thumb/birth.png"
        }
    },
    {
        "name": "birthday",
        "data": {
            "highres": "./images/birthday.png",
            "thumb": "./thumb/birthday.png"
        }
    },
    {
        "name": "bit",
        "data": {
            "highres": "./images/bit.png",
            "thumb": "./thumb/bit.png"
        }
    },
    {
        "name": "bite",
        "data": {
            "highres": "./images/bite.png",
            "thumb": "./thumb/bite.png"
        }
    },
    {
        "name": "black",
        "data": {
            "highres": "./images/black.png",
            "thumb": "./thumb/black.png"
        }
    },
    {
        "name": "blank",
        "data": {
            "highres": "./images/blank.png",
            "thumb": "./thumb/blank.png"
        }
    },
    {
        "name": "blanket",
        "data": {
            "highres": "./images/blanket.png",
            "thumb": "./thumb/blanket.png"
        }
    },
    {
        "name": "blew",
        "data": {
            "highres": "./images/blew.png",
            "thumb": "./thumb/blew.png"
        }
    },
    {
        "name": "blind",
        "data": {
            "highres": "./images/blind.png",
            "thumb": "./thumb/blind.png"
        }
    },
    {
        "name": "block",
        "data": {
            "highres": "./images/block.png",
            "thumb": "./thumb/block.png"
        }
    },
    {
        "name": "blood",
        "data": {
            "highres": "./images/blood.png",
            "thumb": "./thumb/blood.png"
        }
    },
    {
        "name": "blow",
        "data": {
            "highres": "./images/blow.png",
            "thumb": "./thumb/blow.png"
        }
    },
    {
        "name": "blue",
        "data": {
            "highres": "./images/blue.png",
            "thumb": "./thumb/blue.png"
        }
    },
    {
        "name": "board",
        "data": {
            "highres": "./images/board.png",
            "thumb": "./thumb/board.png"
        }
    },
    {
        "name": "boat",
        "data": {
            "highres": "./images/boat.png",
            "thumb": "./thumb/boat.png"
        }
    },
    {
        "name": "body",
        "data": {
            "highres": "./images/body.png",
            "thumb": "./thumb/body.png"
        }
    },
    {
        "name": "bone",
        "data": {
            "highres": "./images/bone.png",
            "thumb": "./thumb/bone.png"
        }
    },
    {
        "name": "book",
        "data": {
            "highres": "./images/book.png",
            "thumb": "./thumb/book.png"
        }
    },
    {
        "name": "border",
        "data": {
            "highres": "./images/border.png",
            "thumb": "./thumb/border.png"
        }
    },
    {
        "name": "born",
        "data": {
            "highres": "./images/born.png",
            "thumb": "./thumb/born.png"
        }
    },
    {
        "name": "both",
        "data": {
            "highres": "./images/both.png",
            "thumb": "./thumb/both.png"
        }
    },
    {
        "name": "bottle",
        "data": {
            "highres": "./images/bottle.png",
            "thumb": "./thumb/bottle.png"
        }
    },
    {
        "name": "bottom",
        "data": {
            "highres": "./images/bottom.png",
            "thumb": "./thumb/bottom.png"
        }
    },
    {
        "name": "bound",
        "data": {
            "highres": "./images/bound.png",
            "thumb": "./thumb/bound.png"
        }
    },
    {
        "name": "bow",
        "data": {
            "highres": "./images/bow.png",
            "thumb": "./thumb/bow.png"
        }
    },
    {
        "name": "bowl",
        "data": {
            "highres": "./images/bowl.png",
            "thumb": "./thumb/bowl.png"
        }
    },
    {
        "name": "box",
        "data": {
            "highres": "./images/box.png",
            "thumb": "./thumb/box.png"
        }
    },
    {
        "name": "boy",
        "data": {
            "highres": "./images/boy.png",
            "thumb": "./thumb/boy.png"
        }
    },
    {
        "name": "brain",
        "data": {
            "highres": "./images/brain.png",
            "thumb": "./thumb/brain.png"
        }
    },
    {
        "name": "branch",
        "data": {
            "highres": "./images/branch.png",
            "thumb": "./thumb/branch.png"
        }
    },
    {
        "name": "brass",
        "data": {
            "highres": "./images/brass.png",
            "thumb": "./thumb/brass.png"
        }
    },
    {
        "name": "brave",
        "data": {
            "highres": "./images/brave.png",
            "thumb": "./thumb/brave.png"
        }
    },
    {
        "name": "bread",
        "data": {
            "highres": "./images/bread.png",
            "thumb": "./thumb/bread.png"
        }
    },
    {
        "name": "break",
        "data": {
            "highres": "./images/break.png",
            "thumb": "./thumb/break.png"
        }
    },
    {
        "name": "breakfast",
        "data": {
            "highres": "./images/breakfast.png",
            "thumb": "./thumb/breakfast.png"
        }
    },
    {
        "name": "breath",
        "data": {
            "highres": "./images/breath.png",
            "thumb": "./thumb/breath.png"
        }
    },
    {
        "name": "breathe",
        "data": {
            "highres": "./images/breathe.png",
            "thumb": "./thumb/breathe.png"
        }
    },
    {
        "name": "breathing",
        "data": {
            "highres": "./images/breathing.png",
            "thumb": "./thumb/breathing.png"
        }
    },
    {
        "name": "breeze",
        "data": {
            "highres": "./images/breeze.png",
            "thumb": "./thumb/breeze.png"
        }
    },
    {
        "name": "brick",
        "data": {
            "highres": "./images/brick.png",
            "thumb": "./thumb/brick.png"
        }
    },
    {
        "name": "bridge",
        "data": {
            "highres": "./images/bridge.png",
            "thumb": "./thumb/bridge.png"
        }
    },
    {
        "name": "brief",
        "data": {
            "highres": "./images/brief.png",
            "thumb": "./thumb/brief.png"
        }
    },
    {
        "name": "bright",
        "data": {
            "highres": "./images/bright.png",
            "thumb": "./thumb/bright.png"
        }
    },
    {
        "name": "bring",
        "data": {
            "highres": "./images/bring.png",
            "thumb": "./thumb/bring.png"
        }
    },
    {
        "name": "broad",
        "data": {
            "highres": "./images/broad.png",
            "thumb": "./thumb/broad.png"
        }
    },
    {
        "name": "broke",
        "data": {
            "highres": "./images/broke.png",
            "thumb": "./thumb/broke.png"
        }
    },
    {
        "name": "broken",
        "data": {
            "highres": "./images/broken.png",
            "thumb": "./thumb/broken.png"
        }
    },
    {
        "name": "brother",
        "data": {
            "highres": "./images/brother.png",
            "thumb": "./thumb/brother.png"
        }
    },
    {
        "name": "brought",
        "data": {
            "highres": "./images/brought.png",
            "thumb": "./thumb/brought.png"
        }
    },
    {
        "name": "brown",
        "data": {
            "highres": "./images/brown.png",
            "thumb": "./thumb/brown.png"
        }
    },
    {
        "name": "brush",
        "data": {
            "highres": "./images/brush.png",
            "thumb": "./thumb/brush.png"
        }
    },
    {
        "name": "buffalo",
        "data": {
            "highres": "./images/buffalo.png",
            "thumb": "./thumb/buffalo.png"
        }
    },
    {
        "name": "build",
        "data": {
            "highres": "./images/build.png",
            "thumb": "./thumb/build.png"
        }
    },
    {
        "name": "building",
        "data": {
            "highres": "./images/building.png",
            "thumb": "./thumb/building.png"
        }
    },
    {
        "name": "built",
        "data": {
            "highres": "./images/built.png",
            "thumb": "./thumb/built.png"
        }
    },
    {
        "name": "buried",
        "data": {
            "highres": "./images/buried.png",
            "thumb": "./thumb/buried.png"
        }
    },
    {
        "name": "burn",
        "data": {
            "highres": "./images/burn.png",
            "thumb": "./thumb/burn.png"
        }
    },
    {
        "name": "burst",
        "data": {
            "highres": "./images/burst.png",
            "thumb": "./thumb/burst.png"
        }
    },
    {
        "name": "bus",
        "data": {
            "highres": "./images/bus.png",
            "thumb": "./thumb/bus.png"
        }
    },
    {
        "name": "bush",
        "data": {
            "highres": "./images/bush.png",
            "thumb": "./thumb/bush.png"
        }
    },
    {
        "name": "business",
        "data": {
            "highres": "./images/business.png",
            "thumb": "./thumb/business.png"
        }
    },
    {
        "name": "busy",
        "data": {
            "highres": "./images/busy.png",
            "thumb": "./thumb/busy.png"
        }
    },
    {
        "name": "but",
        "data": {
            "highres": "./images/but.png",
            "thumb": "./thumb/but.png"
        }
    },
    {
        "name": "butter",
        "data": {
            "highres": "./images/butter.png",
            "thumb": "./thumb/butter.png"
        }
    },
    {
        "name": "buy",
        "data": {
            "highres": "./images/buy.png",
            "thumb": "./thumb/buy.png"
        }
    },
    {
        "name": "by",
        "data": {
            "highres": "./images/by.png",
            "thumb": "./thumb/by.png"
        }
    },
    {
        "name": "cabin",
        "data": {
            "highres": "./images/cabin.png",
            "thumb": "./thumb/cabin.png"
        }
    },
    {
        "name": "cage",
        "data": {
            "highres": "./images/cage.png",
            "thumb": "./thumb/cage.png"
        }
    },
    {
        "name": "cake",
        "data": {
            "highres": "./images/cake.png",
            "thumb": "./thumb/cake.png"
        }
    },
    {
        "name": "call",
        "data": {
            "highres": "./images/call.png",
            "thumb": "./thumb/call.png"
        }
    },
    {
        "name": "calm",
        "data": {
            "highres": "./images/calm.png",
            "thumb": "./thumb/calm.png"
        }
    },
    {
        "name": "came",
        "data": {
            "highres": "./images/came.png",
            "thumb": "./thumb/came.png"
        }
    },
    {
        "name": "camera",
        "data": {
            "highres": "./images/camera.png",
            "thumb": "./thumb/camera.png"
        }
    },
    {
        "name": "camp",
        "data": {
            "highres": "./images/camp.png",
            "thumb": "./thumb/camp.png"
        }
    },
    {
        "name": "can",
        "data": {
            "highres": "./images/can.png",
            "thumb": "./thumb/can.png"
        }
    },
    {
        "name": "canal",
        "data": {
            "highres": "./images/canal.png",
            "thumb": "./thumb/canal.png"
        }
    },
    {
        "name": "cannot",
        "data": {
            "highres": "./images/cannot.png",
            "thumb": "./thumb/cannot.png"
        }
    },
    {
        "name": "cap",
        "data": {
            "highres": "./images/cap.png",
            "thumb": "./thumb/cap.png"
        }
    },
    {
        "name": "capital",
        "data": {
            "highres": "./images/capital.png",
            "thumb": "./thumb/capital.png"
        }
    },
    {
        "name": "captain",
        "data": {
            "highres": "./images/captain.png",
            "thumb": "./thumb/captain.png"
        }
    },
    {
        "name": "captured",
        "data": {
            "highres": "./images/captured.png",
            "thumb": "./thumb/captured.png"
        }
    },
    {
        "name": "car",
        "data": {
            "highres": "./images/car.png",
            "thumb": "./thumb/car.png"
        }
    },
    {
        "name": "carbon",
        "data": {
            "highres": "./images/carbon.png",
            "thumb": "./thumb/carbon.png"
        }
    },
    {
        "name": "card",
        "data": {
            "highres": "./images/card.png",
            "thumb": "./thumb/card.png"
        }
    },
    {
        "name": "care",
        "data": {
            "highres": "./images/care.png",
            "thumb": "./thumb/care.png"
        }
    },
    {
        "name": "careful",
        "data": {
            "highres": "./images/careful.png",
            "thumb": "./thumb/careful.png"
        }
    },
    {
        "name": "carefully",
        "data": {
            "highres": "./images/carefully.png",
            "thumb": "./thumb/carefully.png"
        }
    },
    {
        "name": "carried",
        "data": {
            "highres": "./images/carried.png",
            "thumb": "./thumb/carried.png"
        }
    },
    {
        "name": "carry",
        "data": {
            "highres": "./images/carry.png",
            "thumb": "./thumb/carry.png"
        }
    },
    {
        "name": "case",
        "data": {
            "highres": "./images/case.png",
            "thumb": "./thumb/case.png"
        }
    },
    {
        "name": "cast",
        "data": {
            "highres": "./images/cast.png",
            "thumb": "./thumb/cast.png"
        }
    },
    {
        "name": "castle",
        "data": {
            "highres": "./images/castle.png",
            "thumb": "./thumb/castle.png"
        }
    },
    {
        "name": "cat",
        "data": {
            "highres": "./images/cat.png",
            "thumb": "./thumb/cat.png"
        }
    },
    {
        "name": "catch",
        "data": {
            "highres": "./images/catch.png",
            "thumb": "./thumb/catch.png"
        }
    },
    {
        "name": "cattle",
        "data": {
            "highres": "./images/cattle.png",
            "thumb": "./thumb/cattle.png"
        }
    },
    {
        "name": "caught",
        "data": {
            "highres": "./images/caught.png",
            "thumb": "./thumb/caught.png"
        }
    },
    {
        "name": "cause",
        "data": {
            "highres": "./images/cause.png",
            "thumb": "./thumb/cause.png"
        }
    },
    {
        "name": "cave",
        "data": {
            "highres": "./images/cave.png",
            "thumb": "./thumb/cave.png"
        }
    },
    {
        "name": "cell",
        "data": {
            "highres": "./images/cell.png",
            "thumb": "./thumb/cell.png"
        }
    },
    {
        "name": "cent",
        "data": {
            "highres": "./images/cent.png",
            "thumb": "./thumb/cent.png"
        }
    },
    {
        "name": "center",
        "data": {
            "highres": "./images/center.png",
            "thumb": "./thumb/center.png"
        }
    },
    {
        "name": "central",
        "data": {
            "highres": "./images/central.png",
            "thumb": "./thumb/central.png"
        }
    },
    {
        "name": "century",
        "data": {
            "highres": "./images/century.png",
            "thumb": "./thumb/century.png"
        }
    },
    {
        "name": "certain",
        "data": {
            "highres": "./images/certain.png",
            "thumb": "./thumb/certain.png"
        }
    },
    {
        "name": "certainly",
        "data": {
            "highres": "./images/certainly.png",
            "thumb": "./thumb/certainly.png"
        }
    },
    {
        "name": "chain",
        "data": {
            "highres": "./images/chain.png",
            "thumb": "./thumb/chain.png"
        }
    },
    {
        "name": "chair",
        "data": {
            "highres": "./images/chair.png",
            "thumb": "./thumb/chair.png"
        }
    },
    {
        "name": "chamber",
        "data": {
            "highres": "./images/chamber.png",
            "thumb": "./thumb/chamber.png"
        }
    },
    {
        "name": "chance",
        "data": {
            "highres": "./images/chance.png",
            "thumb": "./thumb/chance.png"
        }
    },
    {
        "name": "change",
        "data": {
            "highres": "./images/change.png",
            "thumb": "./thumb/change.png"
        }
    },
    {
        "name": "changing",
        "data": {
            "highres": "./images/changing.png",
            "thumb": "./thumb/changing.png"
        }
    },
    {
        "name": "chapter",
        "data": {
            "highres": "./images/chapter.png",
            "thumb": "./thumb/chapter.png"
        }
    },
    {
        "name": "character",
        "data": {
            "highres": "./images/character.png",
            "thumb": "./thumb/character.png"
        }
    },
    {
        "name": "characteristic",
        "data": {
            "highres": "./images/characteristic.png",
            "thumb": "./thumb/characteristic.png"
        }
    },
    {
        "name": "charge",
        "data": {
            "highres": "./images/charge.png",
            "thumb": "./thumb/charge.png"
        }
    },
    {
        "name": "chart",
        "data": {
            "highres": "./images/chart.png",
            "thumb": "./thumb/chart.png"
        }
    },
    {
        "name": "check",
        "data": {
            "highres": "./images/check.png",
            "thumb": "./thumb/check.png"
        }
    },
    {
        "name": "cheese",
        "data": {
            "highres": "./images/cheese.png",
            "thumb": "./thumb/cheese.png"
        }
    },
    {
        "name": "chemical",
        "data": {
            "highres": "./images/chemical.png",
            "thumb": "./thumb/chemical.png"
        }
    },
    {
        "name": "chest",
        "data": {
            "highres": "./images/chest.png",
            "thumb": "./thumb/chest.png"
        }
    },
    {
        "name": "chicken",
        "data": {
            "highres": "./images/chicken.png",
            "thumb": "./thumb/chicken.png"
        }
    },
    {
        "name": "chief",
        "data": {
            "highres": "./images/chief.png",
            "thumb": "./thumb/chief.png"
        }
    },
    {
        "name": "child",
        "data": {
            "highres": "./images/child.png",
            "thumb": "./thumb/child.png"
        }
    },
    {
        "name": "children",
        "data": {
            "highres": "./images/children.png",
            "thumb": "./thumb/children.png"
        }
    },
    {
        "name": "choice",
        "data": {
            "highres": "./images/choice.png",
            "thumb": "./thumb/choice.png"
        }
    },
    {
        "name": "choose",
        "data": {
            "highres": "./images/choose.png",
            "thumb": "./thumb/choose.png"
        }
    },
    {
        "name": "chose",
        "data": {
            "highres": "./images/chose.png",
            "thumb": "./thumb/chose.png"
        }
    },
    {
        "name": "chosen",
        "data": {
            "highres": "./images/chosen.png",
            "thumb": "./thumb/chosen.png"
        }
    },
    {
        "name": "church",
        "data": {
            "highres": "./images/church.png",
            "thumb": "./thumb/church.png"
        }
    },
    {
        "name": "circle",
        "data": {
            "highres": "./images/circle.png",
            "thumb": "./thumb/circle.png"
        }
    },
    {
        "name": "circus",
        "data": {
            "highres": "./images/circus.png",
            "thumb": "./thumb/circus.png"
        }
    },
    {
        "name": "citizen",
        "data": {
            "highres": "./images/citizen.png",
            "thumb": "./thumb/citizen.png"
        }
    },
    {
        "name": "city",
        "data": {
            "highres": "./images/city.png",
            "thumb": "./thumb/city.png"
        }
    },
    {
        "name": "class",
        "data": {
            "highres": "./images/class.png",
            "thumb": "./thumb/class.png"
        }
    },
    {
        "name": "classroom",
        "data": {
            "highres": "./images/classroom.png",
            "thumb": "./thumb/classroom.png"
        }
    },
    {
        "name": "claws",
        "data": {
            "highres": "./images/claws.png",
            "thumb": "./thumb/claws.png"
        }
    },
    {
        "name": "clay",
        "data": {
            "highres": "./images/clay.png",
            "thumb": "./thumb/clay.png"
        }
    },
    {
        "name": "clean",
        "data": {
            "highres": "./images/clean.png",
            "thumb": "./thumb/clean.png"
        }
    },
    {
        "name": "clear",
        "data": {
            "highres": "./images/clear.png",
            "thumb": "./thumb/clear.png"
        }
    },
    {
        "name": "clearly",
        "data": {
            "highres": "./images/clearly.png",
            "thumb": "./thumb/clearly.png"
        }
    },
    {
        "name": "climate",
        "data": {
            "highres": "./images/climate.png",
            "thumb": "./thumb/climate.png"
        }
    },
    {
        "name": "climb",
        "data": {
            "highres": "./images/climb.png",
            "thumb": "./thumb/climb.png"
        }
    },
    {
        "name": "clock",
        "data": {
            "highres": "./images/clock.png",
            "thumb": "./thumb/clock.png"
        }
    },
    {
        "name": "close",
        "data": {
            "highres": "./images/close.png",
            "thumb": "./thumb/close.png"
        }
    },
    {
        "name": "closely",
        "data": {
            "highres": "./images/closely.png",
            "thumb": "./thumb/closely.png"
        }
    },
    {
        "name": "closer",
        "data": {
            "highres": "./images/closer.png",
            "thumb": "./thumb/closer.png"
        }
    },
    {
        "name": "cloth",
        "data": {
            "highres": "./images/cloth.png",
            "thumb": "./thumb/cloth.png"
        }
    },
    {
        "name": "clothes",
        "data": {
            "highres": "./images/clothes.png",
            "thumb": "./thumb/clothes.png"
        }
    },
    {
        "name": "clothing",
        "data": {
            "highres": "./images/clothing.png",
            "thumb": "./thumb/clothing.png"
        }
    },
    {
        "name": "cloud",
        "data": {
            "highres": "./images/cloud.png",
            "thumb": "./thumb/cloud.png"
        }
    },
    {
        "name": "club",
        "data": {
            "highres": "./images/club.png",
            "thumb": "./thumb/club.png"
        }
    },
    {
        "name": "coach",
        "data": {
            "highres": "./images/coach.png",
            "thumb": "./thumb/coach.png"
        }
    },
    {
        "name": "coal",
        "data": {
            "highres": "./images/coal.png",
            "thumb": "./thumb/coal.png"
        }
    },
    {
        "name": "coast",
        "data": {
            "highres": "./images/coast.png",
            "thumb": "./thumb/coast.png"
        }
    },
    {
        "name": "coat",
        "data": {
            "highres": "./images/coat.png",
            "thumb": "./thumb/coat.png"
        }
    },
    {
        "name": "coffee",
        "data": {
            "highres": "./images/coffee.png",
            "thumb": "./thumb/coffee.png"
        }
    },
    {
        "name": "cold",
        "data": {
            "highres": "./images/cold.png",
            "thumb": "./thumb/cold.png"
        }
    },
    {
        "name": "collect",
        "data": {
            "highres": "./images/collect.png",
            "thumb": "./thumb/collect.png"
        }
    },
    {
        "name": "college",
        "data": {
            "highres": "./images/college.png",
            "thumb": "./thumb/college.png"
        }
    },
    {
        "name": "colony",
        "data": {
            "highres": "./images/colony.png",
            "thumb": "./thumb/colony.png"
        }
    },
    {
        "name": "color",
        "data": {
            "highres": "./images/color.png",
            "thumb": "./thumb/color.png"
        }
    },
    {
        "name": "column",
        "data": {
            "highres": "./images/column.png",
            "thumb": "./thumb/column.png"
        }
    },
    {
        "name": "combination",
        "data": {
            "highres": "./images/combination.png",
            "thumb": "./thumb/combination.png"
        }
    },
    {
        "name": "combine",
        "data": {
            "highres": "./images/combine.png",
            "thumb": "./thumb/combine.png"
        }
    },
    {
        "name": "come",
        "data": {
            "highres": "./images/come.png",
            "thumb": "./thumb/come.png"
        }
    },
    {
        "name": "comfortable",
        "data": {
            "highres": "./images/comfortable.png",
            "thumb": "./thumb/comfortable.png"
        }
    },
    {
        "name": "coming",
        "data": {
            "highres": "./images/coming.png",
            "thumb": "./thumb/coming.png"
        }
    },
    {
        "name": "command",
        "data": {
            "highres": "./images/command.png",
            "thumb": "./thumb/command.png"
        }
    },
    {
        "name": "common",
        "data": {
            "highres": "./images/common.png",
            "thumb": "./thumb/common.png"
        }
    },
    {
        "name": "community",
        "data": {
            "highres": "./images/community.png",
            "thumb": "./thumb/community.png"
        }
    },
    {
        "name": "company",
        "data": {
            "highres": "./images/company.png",
            "thumb": "./thumb/company.png"
        }
    },
    {
        "name": "compare",
        "data": {
            "highres": "./images/compare.png",
            "thumb": "./thumb/compare.png"
        }
    },
    {
        "name": "compass",
        "data": {
            "highres": "./images/compass.png",
            "thumb": "./thumb/compass.png"
        }
    },
    {
        "name": "complete",
        "data": {
            "highres": "./images/complete.png",
            "thumb": "./thumb/complete.png"
        }
    },
    {
        "name": "completely",
        "data": {
            "highres": "./images/completely.png",
            "thumb": "./thumb/completely.png"
        }
    },
    {
        "name": "complex",
        "data": {
            "highres": "./images/complex.png",
            "thumb": "./thumb/complex.png"
        }
    },
    {
        "name": "composed",
        "data": {
            "highres": "./images/composed.png",
            "thumb": "./thumb/composed.png"
        }
    },
    {
        "name": "composition",
        "data": {
            "highres": "./images/composition.png",
            "thumb": "./thumb/composition.png"
        }
    },
    {
        "name": "compound",
        "data": {
            "highres": "./images/compound.png",
            "thumb": "./thumb/compound.png"
        }
    },
    {
        "name": "concerned",
        "data": {
            "highres": "./images/concerned.png",
            "thumb": "./thumb/concerned.png"
        }
    },
    {
        "name": "condition",
        "data": {
            "highres": "./images/condition.png",
            "thumb": "./thumb/condition.png"
        }
    },
    {
        "name": "congress",
        "data": {
            "highres": "./images/congress.png",
            "thumb": "./thumb/congress.png"
        }
    },
    {
        "name": "connected",
        "data": {
            "highres": "./images/connected.png",
            "thumb": "./thumb/connected.png"
        }
    },
    {
        "name": "consider",
        "data": {
            "highres": "./images/consider.png",
            "thumb": "./thumb/consider.png"
        }
    },
    {
        "name": "consist",
        "data": {
            "highres": "./images/consist.png",
            "thumb": "./thumb/consist.png"
        }
    },
    {
        "name": "consonant",
        "data": {
            "highres": "./images/consonant.png",
            "thumb": "./thumb/consonant.png"
        }
    },
    {
        "name": "constantly",
        "data": {
            "highres": "./images/constantly.png",
            "thumb": "./thumb/constantly.png"
        }
    },
    {
        "name": "construction",
        "data": {
            "highres": "./images/construction.png",
            "thumb": "./thumb/construction.png"
        }
    },
    {
        "name": "contain",
        "data": {
            "highres": "./images/contain.png",
            "thumb": "./thumb/contain.png"
        }
    },
    {
        "name": "continent",
        "data": {
            "highres": "./images/continent.png",
            "thumb": "./thumb/continent.png"
        }
    },
    {
        "name": "continued",
        "data": {
            "highres": "./images/continued.png",
            "thumb": "./thumb/continued.png"
        }
    },
    {
        "name": "contrast",
        "data": {
            "highres": "./images/contrast.png",
            "thumb": "./thumb/contrast.png"
        }
    },
    {
        "name": "control",
        "data": {
            "highres": "./images/control.png",
            "thumb": "./thumb/control.png"
        }
    },
    {
        "name": "conversation",
        "data": {
            "highres": "./images/conversation.png",
            "thumb": "./thumb/conversation.png"
        }
    },
    {
        "name": "cook",
        "data": {
            "highres": "./images/cook.png",
            "thumb": "./thumb/cook.png"
        }
    },
    {
        "name": "cookies",
        "data": {
            "highres": "./images/cookies.png",
            "thumb": "./thumb/cookies.png"
        }
    },
    {
        "name": "cool",
        "data": {
            "highres": "./images/cool.png",
            "thumb": "./thumb/cool.png"
        }
    },
    {
        "name": "copper",
        "data": {
            "highres": "./images/copper.png",
            "thumb": "./thumb/copper.png"
        }
    },
    {
        "name": "copy",
        "data": {
            "highres": "./images/copy.png",
            "thumb": "./thumb/copy.png"
        }
    },
    {
        "name": "corn",
        "data": {
            "highres": "./images/corn.png",
            "thumb": "./thumb/corn.png"
        }
    },
    {
        "name": "corner",
        "data": {
            "highres": "./images/corner.png",
            "thumb": "./thumb/corner.png"
        }
    },
    {
        "name": "correct",
        "data": {
            "highres": "./images/correct.png",
            "thumb": "./thumb/correct.png"
        }
    },
    {
        "name": "correctly",
        "data": {
            "highres": "./images/correctly.png",
            "thumb": "./thumb/correctly.png"
        }
    },
    {
        "name": "cost",
        "data": {
            "highres": "./images/cost.png",
            "thumb": "./thumb/cost.png"
        }
    },
    {
        "name": "cotton",
        "data": {
            "highres": "./images/cotton.png",
            "thumb": "./thumb/cotton.png"
        }
    },
    {
        "name": "could",
        "data": {
            "highres": "./images/could.png",
            "thumb": "./thumb/could.png"
        }
    },
    {
        "name": "count",
        "data": {
            "highres": "./images/count.png",
            "thumb": "./thumb/count.png"
        }
    },
    {
        "name": "country",
        "data": {
            "highres": "./images/country.png",
            "thumb": "./thumb/country.png"
        }
    },
    {
        "name": "couple",
        "data": {
            "highres": "./images/couple.png",
            "thumb": "./thumb/couple.png"
        }
    },
    {
        "name": "courage",
        "data": {
            "highres": "./images/courage.png",
            "thumb": "./thumb/courage.png"
        }
    },
    {
        "name": "course",
        "data": {
            "highres": "./images/course.png",
            "thumb": "./thumb/course.png"
        }
    },
    {
        "name": "court",
        "data": {
            "highres": "./images/court.png",
            "thumb": "./thumb/court.png"
        }
    },
    {
        "name": "cover",
        "data": {
            "highres": "./images/cover.png",
            "thumb": "./thumb/cover.png"
        }
    },
    {
        "name": "cow",
        "data": {
            "highres": "./images/cow.png",
            "thumb": "./thumb/cow.png"
        }
    },
    {
        "name": "cowboy",
        "data": {
            "highres": "./images/cowboy.png",
            "thumb": "./thumb/cowboy.png"
        }
    },
    {
        "name": "crack",
        "data": {
            "highres": "./images/crack.png",
            "thumb": "./thumb/crack.png"
        }
    },
    {
        "name": "cream",
        "data": {
            "highres": "./images/cream.png",
            "thumb": "./thumb/cream.png"
        }
    },
    {
        "name": "create",
        "data": {
            "highres": "./images/create.png",
            "thumb": "./thumb/create.png"
        }
    },
    {
        "name": "creature",
        "data": {
            "highres": "./images/creature.png",
            "thumb": "./thumb/creature.png"
        }
    },
    {
        "name": "crew",
        "data": {
            "highres": "./images/crew.png",
            "thumb": "./thumb/crew.png"
        }
    },
    {
        "name": "crop",
        "data": {
            "highres": "./images/crop.png",
            "thumb": "./thumb/crop.png"
        }
    },
    {
        "name": "cross",
        "data": {
            "highres": "./images/cross.png",
            "thumb": "./thumb/cross.png"
        }
    },
    {
        "name": "crowd",
        "data": {
            "highres": "./images/crowd.png",
            "thumb": "./thumb/crowd.png"
        }
    },
    {
        "name": "cry",
        "data": {
            "highres": "./images/cry.png",
            "thumb": "./thumb/cry.png"
        }
    },
    {
        "name": "cup",
        "data": {
            "highres": "./images/cup.png",
            "thumb": "./thumb/cup.png"
        }
    },
    {
        "name": "curious",
        "data": {
            "highres": "./images/curious.png",
            "thumb": "./thumb/curious.png"
        }
    },
    {
        "name": "current",
        "data": {
            "highres": "./images/current.png",
            "thumb": "./thumb/current.png"
        }
    },
    {
        "name": "curve",
        "data": {
            "highres": "./images/curve.png",
            "thumb": "./thumb/curve.png"
        }
    },
    {
        "name": "customs",
        "data": {
            "highres": "./images/customs.png",
            "thumb": "./thumb/customs.png"
        }
    },
    {
        "name": "cut",
        "data": {
            "highres": "./images/cut.png",
            "thumb": "./thumb/cut.png"
        }
    },
    {
        "name": "cutting",
        "data": {
            "highres": "./images/cutting.png",
            "thumb": "./thumb/cutting.png"
        }
    },
    {
        "name": "daily",
        "data": {
            "highres": "./images/daily.png",
            "thumb": "./thumb/daily.png"
        }
    },
    {
        "name": "damage",
        "data": {
            "highres": "./images/damage.png",
            "thumb": "./thumb/damage.png"
        }
    },
    {
        "name": "dance",
        "data": {
            "highres": "./images/dance.png",
            "thumb": "./thumb/dance.png"
        }
    },
    {
        "name": "danger",
        "data": {
            "highres": "./images/danger.png",
            "thumb": "./thumb/danger.png"
        }
    },
    {
        "name": "dangerous",
        "data": {
            "highres": "./images/dangerous.png",
            "thumb": "./thumb/dangerous.png"
        }
    },
    {
        "name": "dark",
        "data": {
            "highres": "./images/dark.png",
            "thumb": "./thumb/dark.png"
        }
    },
    {
        "name": "darkness",
        "data": {
            "highres": "./images/darkness.png",
            "thumb": "./thumb/darkness.png"
        }
    },
    {
        "name": "date",
        "data": {
            "highres": "./images/date.png",
            "thumb": "./thumb/date.png"
        }
    },
    {
        "name": "daughter",
        "data": {
            "highres": "./images/daughter.png",
            "thumb": "./thumb/daughter.png"
        }
    },
    {
        "name": "dawn",
        "data": {
            "highres": "./images/dawn.png",
            "thumb": "./thumb/dawn.png"
        }
    },
    {
        "name": "day",
        "data": {
            "highres": "./images/day.png",
            "thumb": "./thumb/day.png"
        }
    },
    {
        "name": "dead",
        "data": {
            "highres": "./images/dead.png",
            "thumb": "./thumb/dead.png"
        }
    },
    {
        "name": "deal",
        "data": {
            "highres": "./images/deal.png",
            "thumb": "./thumb/deal.png"
        }
    },
    {
        "name": "dear",
        "data": {
            "highres": "./images/dear.png",
            "thumb": "./thumb/dear.png"
        }
    },
    {
        "name": "death",
        "data": {
            "highres": "./images/death.png",
            "thumb": "./thumb/death.png"
        }
    },
    {
        "name": "decide",
        "data": {
            "highres": "./images/decide.png",
            "thumb": "./thumb/decide.png"
        }
    },
    {
        "name": "declared",
        "data": {
            "highres": "./images/declared.png",
            "thumb": "./thumb/declared.png"
        }
    },
    {
        "name": "deep",
        "data": {
            "highres": "./images/deep.png",
            "thumb": "./thumb/deep.png"
        }
    },
    {
        "name": "deeply",
        "data": {
            "highres": "./images/deeply.png",
            "thumb": "./thumb/deeply.png"
        }
    },
    {
        "name": "deer",
        "data": {
            "highres": "./images/deer.png",
            "thumb": "./thumb/deer.png"
        }
    },
    {
        "name": "definition",
        "data": {
            "highres": "./images/definition.png",
            "thumb": "./thumb/definition.png"
        }
    },
    {
        "name": "degree",
        "data": {
            "highres": "./images/degree.png",
            "thumb": "./thumb/degree.png"
        }
    },
    {
        "name": "depend",
        "data": {
            "highres": "./images/depend.png",
            "thumb": "./thumb/depend.png"
        }
    },
    {
        "name": "depth",
        "data": {
            "highres": "./images/depth.png",
            "thumb": "./thumb/depth.png"
        }
    },
    {
        "name": "describe",
        "data": {
            "highres": "./images/describe.png",
            "thumb": "./thumb/describe.png"
        }
    },
    {
        "name": "desert",
        "data": {
            "highres": "./images/desert.png",
            "thumb": "./thumb/desert.png"
        }
    },
    {
        "name": "design",
        "data": {
            "highres": "./images/design.png",
            "thumb": "./thumb/design.png"
        }
    },
    {
        "name": "desk",
        "data": {
            "highres": "./images/desk.png",
            "thumb": "./thumb/desk.png"
        }
    },
    {
        "name": "detail",
        "data": {
            "highres": "./images/detail.png",
            "thumb": "./thumb/detail.png"
        }
    },
    {
        "name": "determine",
        "data": {
            "highres": "./images/determine.png",
            "thumb": "./thumb/determine.png"
        }
    },
    {
        "name": "develop",
        "data": {
            "highres": "./images/develop.png",
            "thumb": "./thumb/develop.png"
        }
    },
    {
        "name": "development",
        "data": {
            "highres": "./images/development.png",
            "thumb": "./thumb/development.png"
        }
    },
    {
        "name": "diagram",
        "data": {
            "highres": "./images/diagram.png",
            "thumb": "./thumb/diagram.png"
        }
    },
    {
        "name": "diameter",
        "data": {
            "highres": "./images/diameter.png",
            "thumb": "./thumb/diameter.png"
        }
    },
    {
        "name": "did",
        "data": {
            "highres": "./images/did.png",
            "thumb": "./thumb/did.png"
        }
    },
    {
        "name": "die",
        "data": {
            "highres": "./images/die.png",
            "thumb": "./thumb/die.png"
        }
    },
    {
        "name": "differ",
        "data": {
            "highres": "./images/differ.png",
            "thumb": "./thumb/differ.png"
        }
    },
    {
        "name": "difference",
        "data": {
            "highres": "./images/difference.png",
            "thumb": "./thumb/difference.png"
        }
    },
    {
        "name": "different",
        "data": {
            "highres": "./images/different.png",
            "thumb": "./thumb/different.png"
        }
    },
    {
        "name": "difficult",
        "data": {
            "highres": "./images/difficult.png",
            "thumb": "./thumb/difficult.png"
        }
    },
    {
        "name": "difficulty",
        "data": {
            "highres": "./images/difficulty.png",
            "thumb": "./thumb/difficulty.png"
        }
    },
    {
        "name": "dig",
        "data": {
            "highres": "./images/dig.png",
            "thumb": "./thumb/dig.png"
        }
    },
    {
        "name": "dinner",
        "data": {
            "highres": "./images/dinner.png",
            "thumb": "./thumb/dinner.png"
        }
    },
    {
        "name": "direct",
        "data": {
            "highres": "./images/direct.png",
            "thumb": "./thumb/direct.png"
        }
    },
    {
        "name": "direction",
        "data": {
            "highres": "./images/direction.png",
            "thumb": "./thumb/direction.png"
        }
    },
    {
        "name": "directly",
        "data": {
            "highres": "./images/directly.png",
            "thumb": "./thumb/directly.png"
        }
    },
    {
        "name": "dirt",
        "data": {
            "highres": "./images/dirt.png",
            "thumb": "./thumb/dirt.png"
        }
    },
    {
        "name": "dirty",
        "data": {
            "highres": "./images/dirty.png",
            "thumb": "./thumb/dirty.png"
        }
    },
    {
        "name": "disappear",
        "data": {
            "highres": "./images/disappear.png",
            "thumb": "./thumb/disappear.png"
        }
    },
    {
        "name": "discover",
        "data": {
            "highres": "./images/discover.png",
            "thumb": "./thumb/discover.png"
        }
    },
    {
        "name": "discovery",
        "data": {
            "highres": "./images/discovery.png",
            "thumb": "./thumb/discovery.png"
        }
    },
    {
        "name": "discuss",
        "data": {
            "highres": "./images/discuss.png",
            "thumb": "./thumb/discuss.png"
        }
    },
    {
        "name": "discussion",
        "data": {
            "highres": "./images/discussion.png",
            "thumb": "./thumb/discussion.png"
        }
    },
    {
        "name": "disease",
        "data": {
            "highres": "./images/disease.png",
            "thumb": "./thumb/disease.png"
        }
    },
    {
        "name": "dish",
        "data": {
            "highres": "./images/dish.png",
            "thumb": "./thumb/dish.png"
        }
    },
    {
        "name": "distance",
        "data": {
            "highres": "./images/distance.png",
            "thumb": "./thumb/distance.png"
        }
    },
    {
        "name": "distant",
        "data": {
            "highres": "./images/distant.png",
            "thumb": "./thumb/distant.png"
        }
    },
    {
        "name": "divide",
        "data": {
            "highres": "./images/divide.png",
            "thumb": "./thumb/divide.png"
        }
    },
    {
        "name": "division",
        "data": {
            "highres": "./images/division.png",
            "thumb": "./thumb/division.png"
        }
    },
    {
        "name": "do",
        "data": {
            "highres": "./images/do.png",
            "thumb": "./thumb/do.png"
        }
    },
    {
        "name": "doctor",
        "data": {
            "highres": "./images/doctor.png",
            "thumb": "./thumb/doctor.png"
        }
    },
    {
        "name": "does",
        "data": {
            "highres": "./images/does.png",
            "thumb": "./thumb/does.png"
        }
    },
    {
        "name": "dog",
        "data": {
            "highres": "./images/dog.png",
            "thumb": "./thumb/dog.png"
        }
    },
    {
        "name": "doing",
        "data": {
            "highres": "./images/doing.png",
            "thumb": "./thumb/doing.png"
        }
    },
    {
        "name": "doll",
        "data": {
            "highres": "./images/doll.png",
            "thumb": "./thumb/doll.png"
        }
    },
    {
        "name": "dollar",
        "data": {
            "highres": "./images/dollar.png",
            "thumb": "./thumb/dollar.png"
        }
    },
    {
        "name": "done",
        "data": {
            "highres": "./images/done.png",
            "thumb": "./thumb/done.png"
        }
    },
    {
        "name": "donkey",
        "data": {
            "highres": "./images/donkey.png",
            "thumb": "./thumb/donkey.png"
        }
    },
    {
        "name": "door",
        "data": {
            "highres": "./images/door.png",
            "thumb": "./thumb/door.png"
        }
    },
    {
        "name": "dot",
        "data": {
            "highres": "./images/dot.png",
            "thumb": "./thumb/dot.png"
        }
    },
    {
        "name": "double",
        "data": {
            "highres": "./images/double.png",
            "thumb": "./thumb/double.png"
        }
    },
    {
        "name": "doubt",
        "data": {
            "highres": "./images/doubt.png",
            "thumb": "./thumb/doubt.png"
        }
    },
    {
        "name": "down",
        "data": {
            "highres": "./images/down.png",
            "thumb": "./thumb/down.png"
        }
    },
    {
        "name": "dozen",
        "data": {
            "highres": "./images/dozen.png",
            "thumb": "./thumb/dozen.png"
        }
    },
    {
        "name": "draw",
        "data": {
            "highres": "./images/draw.png",
            "thumb": "./thumb/draw.png"
        }
    },
    {
        "name": "drawn",
        "data": {
            "highres": "./images/drawn.png",
            "thumb": "./thumb/drawn.png"
        }
    },
    {
        "name": "dream",
        "data": {
            "highres": "./images/dream.png",
            "thumb": "./thumb/dream.png"
        }
    },
    {
        "name": "dress",
        "data": {
            "highres": "./images/dress.png",
            "thumb": "./thumb/dress.png"
        }
    },
    {
        "name": "drew",
        "data": {
            "highres": "./images/drew.png",
            "thumb": "./thumb/drew.png"
        }
    },
    {
        "name": "dried",
        "data": {
            "highres": "./images/dried.png",
            "thumb": "./thumb/dried.png"
        }
    },
    {
        "name": "drink",
        "data": {
            "highres": "./images/drink.png",
            "thumb": "./thumb/drink.png"
        }
    },
    {
        "name": "drive",
        "data": {
            "highres": "./images/drive.png",
            "thumb": "./thumb/drive.png"
        }
    },
    {
        "name": "driven",
        "data": {
            "highres": "./images/driven.png",
            "thumb": "./thumb/driven.png"
        }
    },
    {
        "name": "driver",
        "data": {
            "highres": "./images/driver.png",
            "thumb": "./thumb/driver.png"
        }
    },
    {
        "name": "driving",
        "data": {
            "highres": "./images/driving.png",
            "thumb": "./thumb/driving.png"
        }
    },
    {
        "name": "drop",
        "data": {
            "highres": "./images/drop.png",
            "thumb": "./thumb/drop.png"
        }
    },
    {
        "name": "dropped",
        "data": {
            "highres": "./images/dropped.png",
            "thumb": "./thumb/dropped.png"
        }
    },
    {
        "name": "drove",
        "data": {
            "highres": "./images/drove.png",
            "thumb": "./thumb/drove.png"
        }
    },
    {
        "name": "dry",
        "data": {
            "highres": "./images/dry.png",
            "thumb": "./thumb/dry.png"
        }
    },
    {
        "name": "duck",
        "data": {
            "highres": "./images/duck.png",
            "thumb": "./thumb/duck.png"
        }
    },
    {
        "name": "due",
        "data": {
            "highres": "./images/due.png",
            "thumb": "./thumb/due.png"
        }
    },
    {
        "name": "dug",
        "data": {
            "highres": "./images/dug.png",
            "thumb": "./thumb/dug.png"
        }
    },
    {
        "name": "dull",
        "data": {
            "highres": "./images/dull.png",
            "thumb": "./thumb/dull.png"
        }
    },
    {
        "name": "during",
        "data": {
            "highres": "./images/during.png",
            "thumb": "./thumb/during.png"
        }
    },
    {
        "name": "dust",
        "data": {
            "highres": "./images/dust.png",
            "thumb": "./thumb/dust.png"
        }
    },
    {
        "name": "duty",
        "data": {
            "highres": "./images/duty.png",
            "thumb": "./thumb/duty.png"
        }
    },
    {
        "name": "each",
        "data": {
            "highres": "./images/each.png",
            "thumb": "./thumb/each.png"
        }
    },
    {
        "name": "eager",
        "data": {
            "highres": "./images/eager.png",
            "thumb": "./thumb/eager.png"
        }
    },
    {
        "name": "ear",
        "data": {
            "highres": "./images/ear.png",
            "thumb": "./thumb/ear.png"
        }
    },
    {
        "name": "earlier",
        "data": {
            "highres": "./images/earlier.png",
            "thumb": "./thumb/earlier.png"
        }
    },
    {
        "name": "early",
        "data": {
            "highres": "./images/early.png",
            "thumb": "./thumb/early.png"
        }
    },
    {
        "name": "earn",
        "data": {
            "highres": "./images/earn.png",
            "thumb": "./thumb/earn.png"
        }
    },
    {
        "name": "earth",
        "data": {
            "highres": "./images/earth.png",
            "thumb": "./thumb/earth.png"
        }
    },
    {
        "name": "easier",
        "data": {
            "highres": "./images/easier.png",
            "thumb": "./thumb/easier.png"
        }
    },
    {
        "name": "easily",
        "data": {
            "highres": "./images/easily.png",
            "thumb": "./thumb/easily.png"
        }
    }
]